sandi/__init__.py
sandi/__main__.py
sandi/app.py
sandi/attributes/IMG.py
sandi/attributes/PCAM.py
sandi/attributes/__init__.py
sandi/attributes/bins.txt
sandi/functions/BatchProcessing.py
sandi/functions/ExportToCSV.py
sandi/functions/ImageEnhancement.py
sandi/functions/ImportImages.py
sandi/functions/ParticleExtraction.py
sandi/functions/StatisticsComputation.py
sandi/functions/VignetteGeneration.py
sandi/functions/__init__.py
sandi/images/__init__.py
sandi/images/homepage_background.png
sandi/images/logo.ico
sandi/images/logo.png
sandi/pages/__init__.py
sandi/pages/batchprocessingpage.py
sandi/pages/homepage.py
sandi/pages/singleimageprocessingpage.py
sandi/pages/singlestoneprocessingpage.py
sandi-0.1.8.dist-info/licenses/LICENSE
sandi-0.1.8.dist-info/METADATA
sandi-0.1.8.dist-info/WHEEL
sandi-0.1.8.dist-info/top_level.txt
sandi-0.1.8.dist-info/RECORD
