Metadata-Version: 2.4
Name: SANDI
Version: 0.1.8
Summary: Sediment ANalysis & Deliniation through Images
Author-email: Louise Delhaye <ldelhaye@naturalsciences.be>
License-Expression: EUPL-1.2
Project-URL: Homepage, https://github.com/louisejuliedelhaye/SANDI/
Project-URL: Documentation, https://readthedocs.org
Project-URL: Repository, https://github.com/louisejuliedelhaye/SANDI/
Classifier: Programming Language :: Python :: 3
Classifier: Operating System :: OS Independent
Requires-Python: >=3.11
License-File: LICENSE
Dynamic: license-file
